{"type":"View","props":{"width":1000,"height":800},"compId":2,"child":[{"type":"Sprite","props":{"presetID":1,"y":0,"x":0,"name":"next","isPresetRoot":true},"compId":9,"child":[{"type":"Sprite","props":{"y":376,"x":479.8671875,"width":47,"presetID":2,"height":58,"texture":"round2/hong/hong_03.png","name":"hong"},"compId":3},{"type":"Text","props":{"y":391,"x":588,"presetID":3,"fontSize":30,"width":34,"text":"3","name":"life","height":33,"color":"#ff0400","runtime":"laya.display.Text"},"compId":4},{"type":"Text","props":{"y":193,"x":469.5,"width":136,"valign":"middle","presetID":4,"height":72,"align":"center","text":"1-1","name":"text","fontSize":50,"font":"Microsoft YaHei","color":"#ffecec","runtime":"laya.display.Text"},"compId":5}]}],"loadList":["prefab/next.prefab"],"loadList3D":[]}